{
  "schema_version": "1.0.0",
  "analysis_date": "2022-07-18",
  "analysis_uuid": "6bb1da01-3c7c-406b-852b-951bbbcb4abc",
  "package": "linux-oem-5.17-tools-5.17.0-1012",
  "package_version": "5.17.0-1012.13",
  "install_command": "apt-get install -y linux-oem-5.17-tools-5.17.0-1012",
  "entrypoints": [
    "/usr/lib/linux-oem-5.17-tools-5.17.0-1012/acpidbg",
    "/usr/lib/linux-oem-5.17-tools-5.17.0-1012/bpftool",
    "/usr/lib/linux-oem-5.17-tools-5.17.0-1012/cpupower",
    "/usr/lib/linux-oem-5.17-tools-5.17.0-1012/perf",
    "/usr/lib/linux-oem-5.17-tools-5.17.0-1012/turbostat",
    "/usr/lib/linux-oem-5.17-tools-5.17.0-1012/usbip",
    "/usr/lib/linux-oem-5.17-tools-5.17.0-1012/usbipd",
    "/usr/lib/linux-oem-5.17-tools-5.17.0-1012/x86_energy_perf_policy"
  ]
}
